{
  "type": "FeatureCollection",
  "features": [
    {
      "type": "Feature",
      "geometry": {
        "type": "Point",
        "coordinates": [
          172.5472531,
          -43.5097504
        ]
      },
      "properties": {
        "name": "Avonhead Park Cemetery",
        "Address": "Hawthornden Road (1st left off Avonhead Road after Withells Road)",
        "More info": "http://www.ccc.govt.nz/services/cemeteries/operational-cemeteries/avonhead-park-cemetery/",
        "Status": "Open"
      }
    }
  ]
}